dataframe_to_superset/SupersetApi.py
dataframe_to_superset/__init__.py
dataframe_to_superset/py.typed
dataframe_to_superset-0.1.6.dist-info/METADATA
dataframe_to_superset-0.1.6.dist-info/WHEEL
dataframe_to_superset-0.1.6.dist-info/RECORD
