Metadata-Version: 2.4
Name: dataframe-to-superset
Version: 0.1.6
Summary: A Python package to upload pandas DataFrames to Superset for easy visualization.
Project-URL: Homepage, https://github.com/lodu/dataframe-to-superset
Project-URL: Documentation, https://github.com/lodu/dataframe-to-superset/blob/main/README.md
Project-URL: Repository, https://github.com/lodu/dataframe-to-superset
Project-URL: Issues, https://github.com/lodu/dataframe-to-superset/issues
Author-email: lodu <pypi@lodu.dev>
Requires-Python: >=3.10
Requires-Dist: pandas>=2.2.3
Requires-Dist: requests>=2.32.3
